hello_labdata_jp/__init__.py
hello_labdata_jp/_modidx.py
hello_labdata_jp/greetings.py
hello_labdata_jp/jokes.py
hello_labdata_jp-0.0.3.dist-info/LICENSE
hello_labdata_jp-0.0.3.dist-info/METADATA
hello_labdata_jp-0.0.3.dist-info/WHEEL
hello_labdata_jp-0.0.3.dist-info/entry_points.txt
hello_labdata_jp-0.0.3.dist-info/top_level.txt
hello_labdata_jp-0.0.3.dist-info/RECORD
