Metadata-Version: 2.1
Name: hello-labdata-jp
Version: 0.0.3
Summary: Labdata Hello Python Package
Home-page: https://github.com/joaopcnogueira/hello-labdata-jp/
Author: Joao Paulo Nogueira
Author-email: joaopcnogueira@gmail.com
License: Apache Software License 2.0
Keywords: nbdev
Classifier: Development Status :: 3 - Alpha
Classifier: Intended Audience :: Developers
Classifier: Natural Language :: English
Classifier: Programming Language :: Python :: 3.8
Classifier: Programming Language :: Python :: 3.9
Classifier: Programming Language :: Python :: 3.10
Classifier: License :: OSI Approved :: Apache Software License
Requires-Python: >=3.8
License-File: LICENSE
Provides-Extra: dev
